ganntchart/__init__.py
ganntchart/ganntchart.py
ganntchart-1.2.4.dist-info/METADATA
ganntchart-1.2.4.dist-info/WHEEL
ganntchart-1.2.4.dist-info/top_level.txt
ganntchart-1.2.4.dist-info/RECORD
