Metadata-Version: 2.1
Name: ganntchart
Version: 1.2.4
Summary: Draw Gannt Chart with svg format
Home-page: https://github.com/EdwardHong0627/gannt_chart
Author: EdwardHong0627
Author-email: edwardboy0627@gmail.com
License: MIT
Keywords: ganntchart,scheduling
Platform: UNKNOWN
Classifier: Development Status :: 5 - Production/Stable
Classifier: License :: OSI Approved :: MIT License
Classifier: Programming Language :: Python :: 3.4
Classifier: Programming Language :: Python :: 3.5
Classifier: Programming Language :: Python :: 3.6
Classifier: Programming Language :: Python :: 3.7
Classifier: Programming Language :: Python :: 3.8
